nkey/__init__.py
nested_key-0.1.1.dist-info/METADATA
nested_key-0.1.1.dist-info/WHEEL
nested_key-0.1.1.dist-info/top_level.txt
nested_key-0.1.1.dist-info/RECORD
